jixia/__init__.py
jixia/run.py
jixia/structs.py
jixia/walk.py
jixia-1.0.5.dist-info/METADATA
jixia-1.0.5.dist-info/WHEEL
jixia-1.0.5.dist-info/RECORD
